CHANGELOG
LICENSE
MANIFEST.in
README.md
setup.py
stripe/__init__.py
stripe/compat.py
stripe/encoders.py
stripe/errors.py
stripe/transport.py
stripe/utils.py
stripe/api/__init__.py
stripe/api/base.py
stripe/tests/__init__.py
stripe/tests/test_stripe.py
stripe_requests.egg-info/PKG-INFO
stripe_requests.egg-info/SOURCES.txt
stripe_requests.egg-info/dependency_links.txt
stripe_requests.egg-info/requires.txt
stripe_requests.egg-info/top_level.txt