Metadata-Version: 1.1
Name: stripe-requests
Version: 1.9.1-dev
Summary: Stripe python bindings using requests
Home-page: https://github.com/allanlei/stripe-requests
Author: Allan Lei
Author-email: allanlei@helveticode.com
License: The MIT License
